odoo/addons/delivery_carrier_label_batch/README.rst
odoo/addons/delivery_carrier_label_batch/__init__.py
odoo/addons/delivery_carrier_label_batch/__manifest__.py
odoo/addons/delivery_carrier_label_batch/pdf_utils.py
odoo/addons/delivery_carrier_label_batch/zpl_utils.py
odoo/addons/delivery_carrier_label_batch/data/ir.config_parameter.xml
odoo/addons/delivery_carrier_label_batch/i18n/de.po
odoo/addons/delivery_carrier_label_batch/i18n/delivery_carrier_label_batch.pot
odoo/addons/delivery_carrier_label_batch/i18n/fr.po
odoo/addons/delivery_carrier_label_batch/models/__init__.py
odoo/addons/delivery_carrier_label_batch/models/stock_batch_picking.py
odoo/addons/delivery_carrier_label_batch/readme/CONFIGURE.rst
odoo/addons/delivery_carrier_label_batch/readme/CONTRIBUTORS.rst
odoo/addons/delivery_carrier_label_batch/readme/CREDITS.rst
odoo/addons/delivery_carrier_label_batch/readme/DESCRIPTION.rst
odoo/addons/delivery_carrier_label_batch/readme/USAGE.rst
odoo/addons/delivery_carrier_label_batch/security/ir.model.access.csv
odoo/addons/delivery_carrier_label_batch/static/description/icon.png
odoo/addons/delivery_carrier_label_batch/static/description/index.html
odoo/addons/delivery_carrier_label_batch/tests/__init__.py
odoo/addons/delivery_carrier_label_batch/tests/dummy.pdf
odoo/addons/delivery_carrier_label_batch/tests/test_generate_labels.py
odoo/addons/delivery_carrier_label_batch/views/stock_batch_picking.xml
odoo/addons/delivery_carrier_label_batch/wizard/__init__.py
odoo/addons/delivery_carrier_label_batch/wizard/apply_carrier.py
odoo/addons/delivery_carrier_label_batch/wizard/apply_carrier_view.xml
odoo/addons/delivery_carrier_label_batch/wizard/generate_labels.py
odoo/addons/delivery_carrier_label_batch/wizard/generate_labels_view.xml
odoo14_addon_delivery_carrier_label_batch-14.0.1.1.1.dist-info/METADATA
odoo14_addon_delivery_carrier_label_batch-14.0.1.1.1.dist-info/WHEEL
odoo14_addon_delivery_carrier_label_batch-14.0.1.1.1.dist-info/top_level.txt
odoo14_addon_delivery_carrier_label_batch-14.0.1.1.1.dist-info/RECORD
