Metadata-Version: 2.1
Name: odoo14-addon-delivery-carrier-label-batch
Version: 14.0.1.1.1
Summary: Carrier labels - Stock Batch Picking (link)
Home-page: https://github.com/OCA/delivery-carrier
Author: Camptocamp,Odoo Community Association (OCA)
Author-email: support@odoo-community.org
License: AGPL-3
Platform: UNKNOWN
Classifier: Programming Language :: Python
Classifier: Framework :: Odoo
Classifier: Framework :: Odoo :: 14.0
Classifier: License :: OSI Approved :: GNU Affero General Public License v3
Requires-Python: >=3.6
Requires-Dist: PyPDF2
Requires-Dist: odoo14-addon-base-delivery-carrier-label
Requires-Dist: odoo14-addon-stock-picking-batch-extended
Requires-Dist: odoo <14.1dev,>=14.0a
